setup.cfg
setup.py
tgext/__init__.py
tgext.geo.egg-info/PKG-INFO
tgext.geo.egg-info/SOURCES.txt
tgext.geo.egg-info/dependency_links.txt
tgext.geo.egg-info/entry_points.txt
tgext.geo.egg-info/namespace_packages.txt
tgext.geo.egg-info/not-zip-safe
tgext.geo.egg-info/requires.txt
tgext.geo.egg-info/top_level.txt
tgext/geo/__init__.py
tgext/geo/commands.py
tgext/geo/featureserver/__init__.py
tgext/geo/featureserver/controller.py
tgext/geo/featureserver/datasource.py
tgext/geo/paster_templates/__init__.py
tgext/geo/templates/__init__.py
tgext/geo/widgets/__init__.py