Metadata-Version: 1.0
Name: tgext.geo
Version: 0.6.2
Summary: TurboGears Extension for Geographic Applications
Home-page: http://code.google.com/p/tgtools/
Author: Sanjiv Singh
Author-email: singhsanjivk@gmail.com
License: MIT
Keywords: TurboGears2 MapFish PCL GIS Geo
Platform: UNKNOWN
